dirdf/LICENSE
dirdf/README.MD
dirdf/__init__.py
dirdf/requirements.txt
dirdf/thirdparty.json
dirdf-0.11.dist-info/LICENSE.rst
dirdf-0.11.dist-info/METADATA
dirdf-0.11.dist-info/WHEEL
dirdf-0.11.dist-info/top_level.txt
dirdf-0.11.dist-info/RECORD
